{"etag":"\"nxOHAKTVB7baOKsQgTtJIyGxcs8\/uPTc6BoCvcLJKEto4vRISNV5Pl4\"","eventId":null,"kind":"youtube#videoListResponse","nextPageToken":null,"prevPageToken":null,"visitorId":null,"pageInfo":{"resultsPerPage":1,"totalResults":1},"items":[{"etag":"\"nxOHAKTVB7baOKsQgTtJIyGxcs8\/Ovkvh-cLCS5auy1Dy_i_YWsTsko\"","id":"95Rzsn-zjr0","kind":"youtube#video","snippet":{"categoryId":"10","channelId":"UCweazuUMMKdL2wwSyrxla9A","channelTitle":"RaeSremmurdVEVO","defaultAudioLanguage":null,"defaultLanguage":null,"description":"Subscribe for more: http:\/\/smarturl.it\/RaeSremmurdYT\n\"SR3MM\" out now http:\/\/smarturl.it\/SR3MM\n\nMusic video by Rae Sremmurd, Swae Lee, Slim Jxmmi performing Powerglide. \u00a9 2018 Eardruma Records\/Interscope Records\n\n#RaeSremmurd #Powerglide #Vevo","liveBroadcastContent":"none","publishedAt":"2018-03-12T16:00:01.000Z","tags":["Rae","Sremmurd","Swae","Lee","Slim","Jxmmi","Powerglide","Mike","WiLL","Made-It","Hip","Hop","rae sremmurd powerflide","rae sremmurd vevo"],"title":"Rae Sremmurd, Swae Lee, Slim Jxmmi - Powerglide ft. Juicy J (Official Video)","thumbnails":{"default":{"height":90,"url":"https:\/\/i.ytimg.com\/vi\/95Rzsn-zjr0\/default.jpg","width":120},"medium":{"height":180,"url":"https:\/\/i.ytimg.com\/vi\/95Rzsn-zjr0\/mqdefault.jpg","width":320},"high":{"height":360,"url":"https:\/\/i.ytimg.com\/vi\/95Rzsn-zjr0\/hqdefault.jpg","width":480},"standard":{"height":480,"url":"https:\/\/i.ytimg.com\/vi\/95Rzsn-zjr0\/sddefault.jpg","width":640},"maxres":{"height":720,"url":"https:\/\/i.ytimg.com\/vi\/95Rzsn-zjr0\/maxresdefault.jpg","width":1280}},"localized":{"description":"Subscribe for more: http:\/\/smarturl.it\/RaeSremmurdYT\n\"SR3MM\" out now http:\/\/smarturl.it\/SR3MM\n\nMusic video by Rae Sremmurd, Swae Lee, Slim Jxmmi performing Powerglide. \u00a9 2018 Eardruma Records\/Interscope Records\n\n#RaeSremmurd #Powerglide #Vevo","title":"Rae Sremmurd, Swae Lee, Slim Jxmmi - Powerglide ft. Juicy J (Official Video)"}},"contentDetails":{"caption":"true","definition":"hd","dimension":"2d","duration":"PT5M26S","hasCustomThumbnail":null,"licensedContent":true,"projection":"rectangular"},"statistics":{"commentCount":"39051","dislikeCount":"59118","favoriteCount":"0","likeCount":"1164964","viewCount":"165240492"}}]}