{"etag":"\"nxOHAKTVB7baOKsQgTtJIyGxcs8\/D9zqO4bcltTZ3oVstaqeT3yQGOw\"","eventId":null,"kind":"youtube#videoListResponse","nextPageToken":null,"prevPageToken":null,"visitorId":null,"pageInfo":{"resultsPerPage":1,"totalResults":1},"items":[{"etag":"\"nxOHAKTVB7baOKsQgTtJIyGxcs8\/jGePQpqujVYhLXuesD9jMi-nqtY\"","id":"yAkYp0pJ1L0","kind":"youtube#video","snippet":{"categoryId":"10","channelId":"UCpDJl2EmP7Oh90Vylx0dZtA","channelTitle":"Spinnin' Records","defaultAudioLanguage":null,"defaultLanguage":null,"description":"Tungevaag - Peru (LUM!X Remix) is OUT NOW! Like this track? Add it to your favourite Spotify\/Apple Music playlist by clicking HERE: https:\/\/spinninrecords.release.link\/peru-lum-x-remix!YT\n\nMake sure to subscribe to Spinnin' Records: http:\/\/bit.do\/spinnintv \n..and turn on notifications to stay updated with all new uploads!\ud83d\udd14\n\nJoin our Spinnin' Records Top 100 Playlist \u25ba https:\/\/spinninrecords.lnk.to\/top100!YT\n\nFollow Tungevaag:\nhttps:\/\/www.instagram.com\/tungevaag\/\nhttps:\/\/www.youtube.com\/channel\/UCdgCw1DIZnWZfWv3rDxIYtw\n\nFollow LUM!X:\nhttps:\/\/soundcloud.com\/lumix_music\nhttps:\/\/www.instagram.com\/lumix_music\/\n\n---\nThe Spinnin\u2019 Records YouTube channel is the home for all music videos of the world\u2019s leading dance record label!\n\nWe feature the latest music videos by Spinnin\u2019 artists like Oliver Heldens, Sam Feldt, KSHMR, Ummet Ozcan, Blasterjaxx, Merk & Kremont, Timmy Trumpet, Tujamo, Alok, Curbi, Mike Williams, Lucas & Steve, Throttle and many, many more! Expect daily uploads of official music videos, lyric videos and official audio across genres like dance, house, electro house, future house, deep house, big room and trap.\n\nFollow Spinnin\u2019 Records:\nhttps:\/\/open.spotify.com\/user\/spinninrecordsofficial\nhttps:\/\/soundcloud.com\/spinninrecords\nhttps:\/\/facebook.com\/SpinninRecords\nhttps:\/\/instagram.com\/spinninrecords\nhttps:\/\/twitter.com\/SpinninRecords\nhttps:\/\/spinninrecords.com\n\n#Tungevaag\n#LUM!X\n#Spinnin\n#SpinninRecords","liveBroadcastContent":"none","publishedAt":"2020-04-25T09:00:25.000Z","tags":["Spinnin","Spinnin' Records","Spinnin Records","SpinninTV","spinning","spinnin official","tungevaag","peru","tungevaag peru","peru tungevaag","official lyric video","big room","pop dance","tungevaag peru lyrics","tungevaag official","tungevaag raaban peru","spinnin big room","peru tungevaag official","tungevaag new track","tungevaag lyrics","peru lyrics","one night in peru","lum!x","lumix","lum!x remix","peru remix","tungevaag remix","lum!x peru remix","tungevaag peru lum!x remix"],"title":"Tungevaag - Peru (LUM!X Remix) [Official Audio]","thumbnails":{"default":{"height":90,"url":"https:\/\/i.ytimg.com\/vi\/yAkYp0pJ1L0\/default.jpg","width":120},"medium":{"height":180,"url":"https:\/\/i.ytimg.com\/vi\/yAkYp0pJ1L0\/mqdefault.jpg","width":320},"high":{"height":360,"url":"https:\/\/i.ytimg.com\/vi\/yAkYp0pJ1L0\/hqdefault.jpg","width":480},"standard":{"height":480,"url":"https:\/\/i.ytimg.com\/vi\/yAkYp0pJ1L0\/sddefault.jpg","width":640},"maxres":{"height":720,"url":"https:\/\/i.ytimg.com\/vi\/yAkYp0pJ1L0\/maxresdefault.jpg","width":1280}},"localized":{"description":"Tungevaag - Peru (LUM!X Remix) is OUT NOW! Like this track? Add it to your favourite Spotify\/Apple Music playlist by clicking HERE: https:\/\/spinninrecords.release.link\/peru-lum-x-remix!YT\n\nMake sure to subscribe to Spinnin' Records: http:\/\/bit.do\/spinnintv \n..and turn on notifications to stay updated with all new uploads!\ud83d\udd14\n\nJoin our Spinnin' Records Top 100 Playlist \u25ba https:\/\/spinninrecords.lnk.to\/top100!YT\n\nFollow Tungevaag:\nhttps:\/\/www.instagram.com\/tungevaag\/\nhttps:\/\/www.youtube.com\/channel\/UCdgCw1DIZnWZfWv3rDxIYtw\n\nFollow LUM!X:\nhttps:\/\/soundcloud.com\/lumix_music\nhttps:\/\/www.instagram.com\/lumix_music\/\n\n---\nThe Spinnin\u2019 Records YouTube channel is the home for all music videos of the world\u2019s leading dance record label!\n\nWe feature the latest music videos by Spinnin\u2019 artists like Oliver Heldens, Sam Feldt, KSHMR, Ummet Ozcan, Blasterjaxx, Merk & Kremont, Timmy Trumpet, Tujamo, Alok, Curbi, Mike Williams, Lucas & Steve, Throttle and many, many more! Expect daily uploads of official music videos, lyric videos and official audio across genres like dance, house, electro house, future house, deep house, big room and trap.\n\nFollow Spinnin\u2019 Records:\nhttps:\/\/open.spotify.com\/user\/spinninrecordsofficial\nhttps:\/\/soundcloud.com\/spinninrecords\nhttps:\/\/facebook.com\/SpinninRecords\nhttps:\/\/instagram.com\/spinninrecords\nhttps:\/\/twitter.com\/SpinninRecords\nhttps:\/\/spinninrecords.com\n\n#Tungevaag\n#LUM!X\n#Spinnin\n#SpinninRecords","title":"Tungevaag - Peru (LUM!X Remix) [Official Audio]"}},"contentDetails":{"caption":"false","definition":"hd","dimension":"2d","duration":"PT2M38S","hasCustomThumbnail":null,"licensedContent":true,"projection":"rectangular"},"statistics":{"commentCount":"160","dislikeCount":"114","favoriteCount":"0","likeCount":"3470","viewCount":"45650"}}]}