{"etag":"\"nxOHAKTVB7baOKsQgTtJIyGxcs8\/qK5C-iLCR_StgMY6FYIM2VhxsAE\"","eventId":null,"kind":"youtube#videoListResponse","nextPageToken":null,"prevPageToken":null,"visitorId":null,"pageInfo":{"resultsPerPage":1,"totalResults":1},"items":[{"etag":"\"nxOHAKTVB7baOKsQgTtJIyGxcs8\/6RMMi7l_I4M9uL3W41dm_Y5g4ps\"","id":"TiWPRk8u6F8","kind":"youtube#video","snippet":{"categoryId":"10","channelId":"UCsjrSi7xMkKPk4gcLSjFKbA","channelTitle":"asapfergVEVO","defaultAudioLanguage":null,"defaultLanguage":null,"description":"A$AP Ferg - \"Value\" out now!: https:\/\/smarturl.it\/xValue\n\nFollow A$AP Ferg:\nhttps:\/\/instagram.com\/asapferg\nhttps:\/\/twitter.com\/ASAPferg\nhttps:\/\/facebook.com\/asapfergofficial\n\n#ASAPFerg #Value #HipHop","liveBroadcastContent":"none","publishedAt":"2020-04-22T14:00:10.000Z","tags":["Floor Seats album","MadeinTYKO","City Girls","Rico Nasty","Ty Dolla Sign","Ty Dolla $ign","Brent Faiyaz","wigs","dream doll","ASAP Ferg","asap ferg vevo","ferg","asap ferg official","a$ap ferg official","a$ap ferg new video","a$ap ferg","where the dogs at","asap ferg where the dogs at","A$AP Ferg A$AP Rocky","A$AP Ferg Pups","A$AP Rock Pups","A$AP Ferg & MadeinTY","A$AP Ferg","A$AP Worldwide\/Polo Grounds Music\/RCA Records","Rap","Value"],"title":"A$AP Ferg - Value","thumbnails":{"default":{"height":90,"url":"https:\/\/i.ytimg.com\/vi\/TiWPRk8u6F8\/default.jpg","width":120},"medium":{"height":180,"url":"https:\/\/i.ytimg.com\/vi\/TiWPRk8u6F8\/mqdefault.jpg","width":320},"high":{"height":360,"url":"https:\/\/i.ytimg.com\/vi\/TiWPRk8u6F8\/hqdefault.jpg","width":480},"standard":{"height":480,"url":"https:\/\/i.ytimg.com\/vi\/TiWPRk8u6F8\/sddefault.jpg","width":640},"maxres":{"height":720,"url":"https:\/\/i.ytimg.com\/vi\/TiWPRk8u6F8\/maxresdefault.jpg","width":1280}},"localized":{"description":"A$AP Ferg - \"Value\" out now!: https:\/\/smarturl.it\/xValue\n\nFollow A$AP Ferg:\nhttps:\/\/instagram.com\/asapferg\nhttps:\/\/twitter.com\/ASAPferg\nhttps:\/\/facebook.com\/asapfergofficial\n\n#ASAPFerg #Value #HipHop","title":"A$AP Ferg - Value"}},"contentDetails":{"caption":"false","definition":"hd","dimension":"2d","duration":"PT3M36S","hasCustomThumbnail":null,"licensedContent":true,"projection":"rectangular","regionRestriction":{"allowed":["GY","GT","GU","GW","GP","GQ","GR","GS","GL","GM","GN","GH","GI","GD","GE","GF","GG","GA","GB","KM","RE","BL","KN","RO","RW","ZW","RU","RS","BH","BW","BV","JM","BT","BS","BR","BQ","JE","UZ","BZ","BY","UY","BG","BF","BE","BD","BB","BA","UA","BO","BN","BM","UM","BJ","BI","JP","PS","MZ","MX","MY","MV","MW","MT","MU","MR","MS","MP","MQ","MN","MO","ML","MM","MK","MH","MF","MG","MD","ME","MC","MA","AZ","TT","AX","TV","VE","TR","AR","AS","AQ","AW","AT","AU","KP","TG","AI","AO","AL","AM","TM","TL","TO","TN","AF","AG","AD","TJ","LY","LU","LT","LV","LS","LR","LI","ZA","LK","KW","LA","LC","LB","DE","DM","DO","DK","DJ","DZ","UG","WF","OM","WS","KH","KI","CR","CU","VU","CW","CX","CY","CZ","KE","KG","VC","CA","KZ","CC","CD","CF","CG","CH","CI","VI","CK","CL","CM","CN","CO","NZ","NR","NP","NU","NI","NO","NL","NC","NA","NG","NF","NE","KR","YE","FK","FJ","FI","FO","FM","FR","YT","VA","TZ","IR","IS","IQ","IT","TD","QA","TC","TF","ID","IE","IN","IO","IL","IM","TH","JO","CV","EE","EC","EH","ET","ER","ES","VG","US","EG","PH","PK","HR","HU","HT","PN","PA","PE","PG","PF","PY","TK","TW","HK","PR","KY","PT","PW","HN","AE","HM","PM","PL","SA","SB","SC","SD","SE","SG","SH","SI","SJ","SK","SL","SM","SN","SO","SR","SS","ST","SV","SX","SY","SZ","ZM","VN"],"blocked":null}},"statistics":{"commentCount":"1077","dislikeCount":"351","favoriteCount":"0","likeCount":"35369","viewCount":"425827"}}]}