{"etag":"\"nxOHAKTVB7baOKsQgTtJIyGxcs8\/X3St6rc8HDwRlj-9rMYkF3q96dc\"","eventId":null,"kind":"youtube#videoListResponse","nextPageToken":null,"prevPageToken":null,"visitorId":null,"pageInfo":{"resultsPerPage":1,"totalResults":1},"items":[{"etag":"\"nxOHAKTVB7baOKsQgTtJIyGxcs8\/5tOKF4AuD97u01A1Vqsov7ihuso\"","id":"K5tVbVu9Mkg","kind":"youtube#video","snippet":{"categoryId":"23","channelId":"UCiVaa8h9U98hqU9EMkNj9Ng","channelTitle":"emt1287","defaultAudioLanguage":null,"defaultLanguage":null,"description":"remix of a lazy town song mixed with lil jon ...remixed by mastgrr","liveBroadcastContent":"none","publishedAt":"2010-10-04T14:11:38.000Z","tags":["humor","musical","music","funny","cooking","by","the","book","lil","jon"],"title":"cooking by the book remix  ft lil jon","thumbnails":{"default":{"height":90,"url":"https:\/\/i.ytimg.com\/vi\/K5tVbVu9Mkg\/default.jpg","width":120},"medium":{"height":180,"url":"https:\/\/i.ytimg.com\/vi\/K5tVbVu9Mkg\/mqdefault.jpg","width":320},"high":{"height":360,"url":"https:\/\/i.ytimg.com\/vi\/K5tVbVu9Mkg\/hqdefault.jpg","width":480}},"localized":{"description":"remix of a lazy town song mixed with lil jon ...remixed by mastgrr","title":"cooking by the book remix  ft lil jon"}},"contentDetails":{"caption":"false","definition":"sd","dimension":"2d","duration":"PT1M19S","hasCustomThumbnail":null,"licensedContent":false,"projection":"rectangular"},"statistics":{"commentCount":"33278","dislikeCount":"13271","favoriteCount":"0","likeCount":"663031","viewCount":"40268897"}}]}